{
  "day": 24,
  "title": "Evenement et organisation",
  "theme": "행사와 준비",
  "description": "모임과 안내, 장소 운영에 필요한 어휘입니다.",
  "words": [
    {
      "word": "le loyer",
      "partOfSpeech": "noun",
      "meaning": "월세",
      "example": "On rencontre souvent le loyer en preparant un evenement pour plusieurs invites."
    },
    {
      "word": "le client",
      "partOfSpeech": "noun",
      "meaning": "고객",
      "example": "Dans la vraie vie, le client revient souvent en preparant un evenement pour plusieurs invites."
    },
    {
      "word": "la reclamation",
      "partOfSpeech": "noun",
      "meaning": "불만 제기",
      "example": "Je remarque souvent la reclamation en preparant un evenement pour plusieurs invites."
    },
    {
      "word": "la satisfaction",
      "partOfSpeech": "noun",
      "meaning": "만족",
      "example": "On rencontre souvent la satisfaction en preparant un evenement pour plusieurs invites."
    },
    {
      "word": "l'entretien",
      "partOfSpeech": "noun",
      "meaning": "면접",
      "example": "Dans la vraie vie, l'entretien revient souvent en preparant un evenement pour plusieurs invites."
    },
    {
      "word": "l'experience",
      "partOfSpeech": "noun",
      "meaning": "경험",
      "example": "Je remarque souvent l'experience en preparant un evenement pour plusieurs invites."
    },
    {
      "word": "la competence",
      "partOfSpeech": "noun",
      "meaning": "역량",
      "example": "On rencontre souvent la competence en preparant un evenement pour plusieurs invites."
    },
    {
      "word": "la regle",
      "partOfSpeech": "noun",
      "meaning": "규칙",
      "example": "Dans la vraie vie, la regle revient souvent en preparant un evenement pour plusieurs invites."
    },
    {
      "word": "la securite",
      "partOfSpeech": "noun",
      "meaning": "안전",
      "example": "Je remarque souvent la securite en preparant un evenement pour plusieurs invites."
    },
    {
      "word": "l'urgence",
      "partOfSpeech": "noun",
      "meaning": "긴급 상황",
      "example": "On rencontre souvent l'urgence en preparant un evenement pour plusieurs invites."
    },
    {
      "word": "la conclusion",
      "partOfSpeech": "noun",
      "meaning": "결론",
      "example": "Dans la vraie vie, la conclusion revient souvent en preparant un evenement pour plusieurs invites."
    },
    {
      "word": "la condition",
      "partOfSpeech": "noun",
      "meaning": "조건",
      "example": "Je remarque souvent la condition en preparant un evenement pour plusieurs invites."
    },
    {
      "word": "l'exemple",
      "partOfSpeech": "noun",
      "meaning": "예시",
      "example": "On rencontre souvent l'exemple en preparant un evenement pour plusieurs invites."
    },
    {
      "word": "l'accueil",
      "partOfSpeech": "noun",
      "meaning": "맞이함",
      "example": "Dans la vraie vie, l'accueil revient souvent en preparant un evenement pour plusieurs invites."
    },
    {
      "word": "la conversation",
      "partOfSpeech": "noun",
      "meaning": "대화",
      "example": "Je remarque souvent la conversation en preparant un evenement pour plusieurs invites."
    },
    {
      "word": "debattre",
      "partOfSpeech": "verb",
      "meaning": "토론하다",
      "example": "En general, je dois debattre en preparant un evenement pour plusieurs invites."
    },
    {
      "word": "identifier",
      "partOfSpeech": "verb",
      "meaning": "파악하다",
      "example": "Dans cette scene, nous pouvons identifier sans perdre de temps en preparant un evenement pour plusieurs invites."
    },
    {
      "word": "resoudre",
      "partOfSpeech": "verb",
      "meaning": "해결하다",
      "example": "Il faut parfois resoudre naturellement en preparant un evenement pour plusieurs invites."
    },
    {
      "word": "ameliorer",
      "partOfSpeech": "verb",
      "meaning": "개선하다",
      "example": "En general, je dois ameliorer en preparant un evenement pour plusieurs invites."
    },
    {
      "word": "clarifier",
      "partOfSpeech": "verb",
      "meaning": "명확히 하다",
      "example": "Dans cette scene, nous pouvons clarifier sans perdre de temps en preparant un evenement pour plusieurs invites."
    },
    {
      "word": "proposer",
      "partOfSpeech": "verb",
      "meaning": "제안하다",
      "example": "Il faut parfois proposer naturellement en preparant un evenement pour plusieurs invites."
    },
    {
      "word": "justifier",
      "partOfSpeech": "verb",
      "meaning": "정당화하다",
      "example": "En general, je dois justifier en preparant un evenement pour plusieurs invites."
    },
    {
      "word": "conclure",
      "partOfSpeech": "verb",
      "meaning": "결론짓다",
      "example": "Dans cette scene, nous pouvons conclure sans perdre de temps en preparant un evenement pour plusieurs invites."
    },
    {
      "word": "reviser",
      "partOfSpeech": "verb",
      "meaning": "복습하다",
      "example": "Il faut parfois reviser naturellement en preparant un evenement pour plusieurs invites."
    },
    {
      "word": "se concentrer",
      "partOfSpeech": "verb",
      "meaning": "집중하다",
      "example": "En general, je dois se concentrer en preparant un evenement pour plusieurs invites."
    },
    {
      "word": "retenir",
      "partOfSpeech": "verb",
      "meaning": "기억하다",
      "example": "Dans cette scene, nous pouvons retenir sans perdre de temps en preparant un evenement pour plusieurs invites."
    },
    {
      "word": "respecter",
      "partOfSpeech": "verb",
      "meaning": "존중하다",
      "example": "Il faut parfois respecter naturellement en preparant un evenement pour plusieurs invites."
    },
    {
      "word": "coordonner",
      "partOfSpeech": "verb",
      "meaning": "조율하다",
      "example": "En general, je dois coordonner en preparant un evenement pour plusieurs invites."
    },
    {
      "word": "accueillir",
      "partOfSpeech": "verb",
      "meaning": "맞이하다",
      "example": "Dans cette scene, nous pouvons accueillir sans perdre de temps en preparant un evenement pour plusieurs invites."
    },
    {
      "word": "saluer",
      "partOfSpeech": "verb",
      "meaning": "인사하다",
      "example": "Il faut parfois saluer naturellement en preparant un evenement pour plusieurs invites."
    },
    {
      "word": "realiste",
      "partOfSpeech": "adjective",
      "meaning": "현실적인",
      "example": "Il vaut souvent mieux etre realiste en preparant un evenement pour plusieurs invites."
    },
    {
      "word": "festif",
      "partOfSpeech": "adjective",
      "meaning": "축제 분위기의",
      "example": "Rester festif aide beaucoup en preparant un evenement pour plusieurs invites."
    },
    {
      "word": "accueillant",
      "partOfSpeech": "adjective",
      "meaning": "환영하는 분위기의",
      "example": "Essayer d'etre accueillant fait souvent la difference en preparant un evenement pour plusieurs invites."
    },
    {
      "word": "visible",
      "partOfSpeech": "adjective",
      "meaning": "눈에 잘 띄는",
      "example": "Il vaut souvent mieux etre visible en preparant un evenement pour plusieurs invites."
    },
    {
      "word": "lumineux",
      "partOfSpeech": "adjective",
      "meaning": "채광이 좋은",
      "example": "Rester lumineux aide beaucoup en preparant un evenement pour plusieurs invites."
    },
    {
      "word": "renove",
      "partOfSpeech": "adjective",
      "meaning": "수리된",
      "example": "Essayer d'etre renove fait souvent la difference en preparant un evenement pour plusieurs invites."
    },
    {
      "word": "courtois",
      "partOfSpeech": "adjective",
      "meaning": "공손한",
      "example": "Il vaut souvent mieux etre courtois en preparant un evenement pour plusieurs invites."
    },
    {
      "word": "mecontent",
      "partOfSpeech": "adjective",
      "meaning": "불만족한",
      "example": "Rester mecontent aide beaucoup en preparant un evenement pour plusieurs invites."
    },
    {
      "word": "motivant",
      "partOfSpeech": "adjective",
      "meaning": "의욕을 주는",
      "example": "Essayer d'etre motivant fait souvent la difference en preparant un evenement pour plusieurs invites."
    },
    {
      "word": "qualifie",
      "partOfSpeech": "adjective",
      "meaning": "자격을 갖춘",
      "example": "Il vaut souvent mieux etre qualifie en preparant un evenement pour plusieurs invites."
    },
    {
      "word": "sans frais",
      "partOfSpeech": "adverb",
      "meaning": "수수료 없이",
      "example": "On agit souvent sans frais en preparant un evenement pour plusieurs invites."
    },
    {
      "word": "en resume",
      "partOfSpeech": "adverb",
      "meaning": "요약하면",
      "example": "Dans la vraie vie, on fait souvent cela en resume en preparant un evenement pour plusieurs invites."
    },
    {
      "word": "en bref",
      "partOfSpeech": "adverb",
      "meaning": "간단히 말해",
      "example": "On entend souvent cette expression, en bref, en preparant un evenement pour plusieurs invites."
    },
    {
      "word": "en pratique",
      "partOfSpeech": "adverb",
      "meaning": "실제로",
      "example": "On agit souvent en pratique en preparant un evenement pour plusieurs invites."
    },
    {
      "word": "au final",
      "partOfSpeech": "adverb",
      "meaning": "결국",
      "example": "Dans la vraie vie, on fait souvent cela au final en preparant un evenement pour plusieurs invites."
    },
    {
      "word": "par consequent",
      "partOfSpeech": "adverb",
      "meaning": "따라서",
      "example": "On entend souvent cette expression, par consequent, en preparant un evenement pour plusieurs invites."
    },
    {
      "word": "en revanche",
      "partOfSpeech": "adverb",
      "meaning": "반면에",
      "example": "On agit souvent en revanche en preparant un evenement pour plusieurs invites."
    },
    {
      "word": "pourtant",
      "partOfSpeech": "adverb",
      "meaning": "그런데도",
      "example": "Dans la vraie vie, on fait souvent cela pourtant en preparant un evenement pour plusieurs invites."
    },
    {
      "word": "d'ailleurs",
      "partOfSpeech": "adverb",
      "meaning": "게다가",
      "example": "On entend souvent cette expression, d'ailleurs, en preparant un evenement pour plusieurs invites."
    },
    {
      "word": "autrement dit",
      "partOfSpeech": "adverb",
      "meaning": "즉",
      "example": "On agit souvent autrement dit en preparant un evenement pour plusieurs invites."
    }
  ],
  "quiz": [
    {
      "sentence": "Dans la vraie vie, ____ revient souvent en preparant un evenement pour plusieurs invites.",
      "answer": "le client",
      "hint": "고객"
    },
    {
      "sentence": "Dans la vraie vie, ____ revient souvent en preparant un evenement pour plusieurs invites.",
      "answer": "l'entretien",
      "hint": "면접"
    },
    {
      "sentence": "On rencontre souvent ____ en preparant un evenement pour plusieurs invites.",
      "answer": "l'urgence",
      "hint": "긴급 상황"
    },
    {
      "sentence": "Dans la vraie vie, ____ revient souvent en preparant un evenement pour plusieurs invites.",
      "answer": "l'accueil",
      "hint": "맞이함"
    },
    {
      "sentence": "En general, je dois ____ en preparant un evenement pour plusieurs invites.",
      "answer": "ameliorer",
      "hint": "개선하다"
    },
    {
      "sentence": "Dans cette scene, nous pouvons ____ sans perdre de temps en preparant un evenement pour plusieurs invites.",
      "answer": "conclure",
      "hint": "결론짓다"
    },
    {
      "sentence": "Il faut parfois ____ naturellement en preparant un evenement pour plusieurs invites.",
      "answer": "saluer",
      "hint": "인사하다"
    },
    {
      "sentence": "Rester ____ aide beaucoup en preparant un evenement pour plusieurs invites.",
      "answer": "lumineux",
      "hint": "채광이 좋은"
    },
    {
      "sentence": "Dans la vraie vie, on fait souvent cela ____ en preparant un evenement pour plusieurs invites.",
      "answer": "en resume",
      "hint": "요약하면"
    },
    {
      "sentence": "Dans la vraie vie, on fait souvent cela ____ en preparant un evenement pour plusieurs invites.",
      "answer": "pourtant",
      "hint": "그런데도"
    }
  ]
}